README.rst
setup.cfg
setup.py
MySmoll/__init__.py
MySmoll/mysmoll.py
MySmoll.egg-info/PKG-INFO
MySmoll.egg-info/SOURCES.txt
MySmoll.egg-info/dependency_links.txt
MySmoll.egg-info/top_level.txt